{
  "db_name": "PostgreSQL",
  "query": "\n        SELECT user_id, space_id, role as \"role: Role\", joined_at\n        FROM memberships\n        WHERE user_id = $1 AND space_id = $2\n        ",
  "describe": {
    "columns": [
      {
        "ordinal": 0,
        "name": "user_id",
        "type_info": "Uuid"
      },
      {
        "ordinal": 1,
        "name": "space_id",
        "type_info": "Uuid"
      },
      {
        "ordinal": 2,
        "name": "role: Role",
        "type_info": "Text"
      },
      {
        "ordinal": 3,
        "name": "joined_at",
        "type_info": "Timestamptz"
      }
    ],
    "parameters": {
      "Left": [
        "Uuid",
        "Uuid"
      ]
    },
    "nullable": [
      false,
      false,
      false,
      true
    ]
  },
  "hash": "55d963cbcf18ec8e63e62ce9c1b4a00c58342561643d3465cddba460d73cb62a"
}
